riscvflow/RISCVControlFlowBuilder.py
riscvflow/__init__.py
riscvflow/cfg.py
riscvflow/logger.py
riscvflow/node.py
riscvflow/registers.py
riscvflow/traversals.py
riscvflow/utils.py
riscvflow/version.py
riscvflow-0.3.32.dist-info/METADATA
riscvflow-0.3.32.dist-info/WHEEL
riscvflow-0.3.32.dist-info/entry_points.txt
riscvflow-0.3.32.dist-info/top_level.txt
riscvflow-0.3.32.dist-info/RECORD
