Metadata-Version: 2.1
Name: riscvflow
Version: 0.3.32
Summary: A library for control flow graph analysis of RISC-V assembly
Author: Akshit Sharma
Author-email: akshitsharma@mines.edu
Requires-Dist: graphviz
